github_release/__init__.py
github_release/api.py
github_release/github_release.py
github_release/utils.py
github_tagged_release-0.1.0.dist-info/LICENSE
github_tagged_release-0.1.0.dist-info/METADATA
github_tagged_release-0.1.0.dist-info/WHEEL
github_tagged_release-0.1.0.dist-info/entry_points.txt
github_tagged_release-0.1.0.dist-info/top_level.txt
github_tagged_release-0.1.0.dist-info/RECORD
