Metadata-Version: 2.1
Name: github-tagged-release
Version: 0.1.0
Summary: GitHub changelogs using tags for your CircleCI workflow
Home-page: https://github.com/convertelligence/github_tagged_release
Author: Nikolai R Kristiansen
Author-email: nikolaik@gmail.com
License: MIT
Platform: UNKNOWN
Classifier: Programming Language :: Python :: 3
Classifier: License :: OSI Approved :: MIT License
Classifier: Operating System :: OS Independent
Requires-Dist: requests (>=2.18.4)
